Metadata-Version: 2.1
Name: tea-xyz-cl01
Version: 1.0.6
Summary: A simple package for https://app.tea.xyz/. Example tea-xyz - https://github.com/ItzChip/tea-xyz-cl01
Home-page: https://github.com/ItzChip/tea-xyz-cl01
Author: ItzChip
Author-email: bybitakun17@gmail.com
Project-URL: Homepage, https://github.com/ItzChip/tea-xyz-cl01
Project-URL: Source, https://github.com/ItzChip/tea-xyz-cl01
Classifier: License :: OSI Approved :: MIT License
Classifier: Programming Language :: Python :: 3
Requires-Python: >=3.6
Requires-Dist: requests >=2.20.0
Requires-Dist: tea-xyz-cl01
